nhlpy/__init__.py
nhlpy/api/__init__.py
nhlpy/api/game_center.py
nhlpy/api/helpers.py
nhlpy/api/misc.py
nhlpy/api/players.py
nhlpy/api/query/__init__.py
nhlpy/api/query/builder.py
nhlpy/api/query/filters/__init__.py
nhlpy/api/query/filters/decision.py
nhlpy/api/query/filters/draft.py
nhlpy/api/query/filters/experience.py
nhlpy/api/query/filters/franchise.py
nhlpy/api/query/filters/game_type.py
nhlpy/api/query/filters/home_road.py
nhlpy/api/query/filters/nationality.py
nhlpy/api/query/filters/opponent.py
nhlpy/api/query/filters/position.py
nhlpy/api/query/filters/season.py
nhlpy/api/query/filters/shoot_catch.py
nhlpy/api/query/filters/status.py
nhlpy/api/query/sorting/__init__.py
nhlpy/api/query/sorting/sorting_options.py
nhlpy/api/schedule.py
nhlpy/api/standings.py
nhlpy/api/stats.py
nhlpy/api/teams.py
nhlpy/config.py
nhlpy/data/seasonal_information_manifest.json
nhlpy/data/team_stat_ids.json
nhlpy/data/teams_20232024.json
nhlpy/http_client.py
nhlpy/nhl_client.py
nhl_api_py-3.0.2.dist-info/METADATA
nhl_api_py-3.0.2.dist-info/WHEEL
nhl_api_py-3.0.2.dist-info/RECORD
