Metadata-Version: 2.1
Name: nhl-api-py
Version: 3.0.2
Summary: NHL API (Updated for 2025/2026) and EDGE Stats.  For standings, team stats, outcomes, player information.  Contains each individual API endpoint as well as convience methods as well as pythonic query builder for more indepth EDGE stats.
Home-page: https://github.com/coreyjs/nhl-api-py
License: GPL-3.0-or-later
Keywords: nhl,api,wrapper,hockey,sports,edge,edge stats,edge analytics,edge sports,edge hockey,edge nhl,edge nhl stats,edge nhl analytics,edge nhl sports,edge nhl hockey,edge nhl data,edge nhl data analytics,edge nhl data stats,edge nhl data sports,edge nhl data hockey,edge nhl data stats analytics,edge nhl data stats sports,edge nhl data stats hockey,hockey ai,hockey machine learning,nhl ML,nhl AI,nhl machine learning,nhl stats,nhl analytics,nhl sports,nhl hockey,nhl nhl,nhl nhl stats,nhl nhl a
Author: Corey Schaf
Author-email: cschaf@gmail.com
Requires-Python: >=3.9,<4.0
Classifier: Development Status :: 5 - Production/Stable
Classifier: Intended Audience :: Developers
Classifier: Intended Audience :: Education
Classifier: License :: OSI Approved :: GNU General Public License v3 or later (GPLv3+)
Classifier: License :: OSI Approved :: MIT License
Classifier: Programming Language :: Python :: 3
Classifier: Programming Language :: Python :: 3.9
Classifier: Programming Language :: Python :: 3.10
Classifier: Programming Language :: Python :: 3.11
Classifier: Programming Language :: Python :: 3.12
Classifier: Programming Language :: Python :: 3 :: Only
Classifier: Topic :: Software Development :: Libraries
Classifier: Topic :: Software Development :: Libraries :: Application Frameworks
Classifier: Topic :: Software Development :: Libraries :: Python Modules
Requires-Dist: httpx
Project-URL: Repository, https://github.com/coreyjs/nhl-api-py
